text_transform.py
texttransform-0.2.dist-info/LICENSE
texttransform-0.2.dist-info/METADATA
texttransform-0.2.dist-info/WHEEL
texttransform-0.2.dist-info/entry_points.txt
texttransform-0.2.dist-info/top_level.txt
texttransform-0.2.dist-info/RECORD
