Metadata-Version: 2.1
Name: texttransform
Version: 0.2
Summary: A tool to convert sentences between uppercase and lowercase and to format sentences correctly.
Home-page: https://github.com/Genevieveok/texttransform
Author: Genevieve
Author-email: genevieve.okon@rocketmail.com
Classifier: Programming Language :: Python :: 3
Classifier: License :: OSI Approved :: MIT License
Classifier: Operating System :: OS Independent
Requires-Python: >=3.6
License-File: LICENSE
